LICENSE
README.md
cli.py
setup.py
exec_engine/__init__.py
exec_engine/api_executor.py
exec_engine/db_manager.py
exec_engine/docker_sandbox.py
exec_engine/fs_manager.py
exec_engine/negation_manager.py
exec_engine/pipeline.py
exec_engine/utils.py
exec_engine/credentials/__init__.py
exec_engine/credentials/credentials_utils.py
gorilla_execution_engine.egg-info/PKG-INFO
gorilla_execution_engine.egg-info/SOURCES.txt
gorilla_execution_engine.egg-info/dependency_links.txt
gorilla_execution_engine.egg-info/entry_points.txt
gorilla_execution_engine.egg-info/requires.txt
gorilla_execution_engine.egg-info/top_level.txt