Metadata-Version: 2.1
Name: gorilla-execution-engine
Version: 0.0.1
Summary: Gorilla Execution Engine CLI
Home-page: https://github.com/ShishirPatil/gorilla/
Author: Shishir Patil, Tianjun Zhang, Vivian Fang, Noppapon Chalermchockcharoenkit, Roy Huang, Aaron Hao
Author-email: shishirpatil@berkeley.edu
Classifier: Programming Language :: Python :: 3
Classifier: License :: OSI Approved :: Apache Software License
Classifier: Operating System :: OS Independent
Requires-Python: >=3.6
License-File: LICENSE
Requires-Dist: docker
Requires-Dist: uvicorn
Requires-Dist: fastapi
Requires-Dist: docopt==0.6.2
Requires-Dist: google_api_python_client==2.118.0
Requires-Dist: google_auth_oauthlib==1.2.0
Requires-Dist: halo==0.0.31
Requires-Dist: mysql-connector-python
Requires-Dist: openai==1.12.0
Requires-Dist: pandas==2.2.0
Requires-Dist: protobuf==4.25.3
Requires-Dist: pymysql==1.1.0
Requires-Dist: python-dotenv==1.0.1
Requires-Dist: Requests==2.31.0
Requires-Dist: simple-colors
Requires-Dist: cryptography
Requires-Dist: waitress==3.0.0
Requires-Dist: yarg==0.1.9
Requires-Dist: questionary==2.0.1
